mpkg/__init__.py
mpkg/app.py
mpkg/cli.py
mpkg/common.py
mpkg/config.py
mpkg/lnktools.py
mpkg/load.py
mpkg/parse.py
mpkg/utils.py
mpkg/commands/__init__.py
mpkg/commands/cmd_doctor.py
mpkg-0.0.13.dist-info/licenses/LICENSE
mpkg-0.0.13.dist-info/METADATA
mpkg-0.0.13.dist-info/WHEEL
mpkg-0.0.13.dist-info/entry_points.txt
mpkg-0.0.13.dist-info/top_level.txt
mpkg-0.0.13.dist-info/RECORD
