Metadata-Version: 2.4
Name: mpkg
Version: 0.0.13
Summary: A simple package manager.
Home-page: https://github.com/mpkg-project/mpkg
Author: zpcc
Author-email: zp.c@outlook.com
Classifier: Development Status :: 4 - Beta
Classifier: Programming Language :: Python :: 3
Classifier: Programming Language :: Python :: 3 :: Only
Classifier: Programming Language :: Python :: 3.7
Classifier: Programming Language :: Python :: 3.8
Classifier: Programming Language :: Python :: 3.9
Classifier: Programming Language :: Python :: 3.10
Classifier: Programming Language :: Python :: 3.11
Classifier: License :: OSI Approved :: Apache Software License
Requires-Python: >=3.7
License-File: LICENSE
Requires-Dist: lxml>=4.5.0
Requires-Dist: beautifulsoup4>=4.6.3
Requires-Dist: requests>=2.23.0
Requires-Dist: click>=7.0.0
Requires-Dist: loguru>=0.5.1
Requires-Dist: tenacity>=6.0.0
Requires-Dist: semver>=2.8.0
Requires-Dist: pyyaml>=5.3.1
Dynamic: author
Dynamic: author-email
Dynamic: classifier
Dynamic: description
Dynamic: description-content-type
Dynamic: home-page
Dynamic: license-file
Dynamic: requires-dist
Dynamic: requires-python
Dynamic: summary
